sentibank/__init__.py
sentibank/archive.py
sentibank/cli.py
sentibank/logger.py
sentibank/utils.py
sentibank/validate.py
sentibank/dict_arXiv/emos.py
sentibank/dict_arXiv/AFINN/AFINN_v2009.csv
sentibank/dict_arXiv/AFINN/AFINN_v2009.json
sentibank/dict_arXiv/AFINN/AFINN_v2009.pickle
sentibank/dict_arXiv/AFINN/AFINN_v2011.csv
sentibank/dict_arXiv/AFINN/AFINN_v2011.json
sentibank/dict_arXiv/AFINN/AFINN_v2011.pickle
sentibank/dict_arXiv/AFINN/AFINN_v2015.csv
sentibank/dict_arXiv/AFINN/AFINN_v2015.json
sentibank/dict_arXiv/AFINN/AFINN_v2015.pickle
sentibank/dict_arXiv/ANEW/ANEW_v1999.csv
sentibank/dict_arXiv/ANEW/ANEW_v1999_simple.json
sentibank/dict_arXiv/ANEW/ANEW_v1999_simple.pickle
sentibank/dict_arXiv/ANEW/ANEW_v1999_weighted.json
sentibank/dict_arXiv/ANEW/ANEW_v1999_weighted.pickle
sentibank/dict_arXiv/Aigents/Aigents+_v2022.csv
sentibank/dict_arXiv/Aigents/Aigents+_v2022.json
sentibank/dict_arXiv/Aigents/Aigents+_v2022.pickle
sentibank/dict_arXiv/DAL/DAL_v2009.csv
sentibank/dict_arXiv/DAL/DAL_v2009_boosted.json
sentibank/dict_arXiv/DAL/DAL_v2009_boosted.pickle
sentibank/dict_arXiv/DAL/DAL_v2009_norm.json
sentibank/dict_arXiv/DAL/DAL_v2009_norm.pickle
sentibank/dict_arXiv/DED/DED_v2022.csv
sentibank/dict_arXiv/DED/DED_v2022.json
sentibank/dict_arXiv/DED/DED_v2022.pickle
sentibank/dict_arXiv/GeneralInquirer/GeneralInquirer_v2000.csv
sentibank/dict_arXiv/GeneralInquirer/GeneralInquirer_v2000.json
sentibank/dict_arXiv/GeneralInquirer/GeneralInquirer_v2000.pickle
sentibank/dict_arXiv/Henry/Henry_v2006.csv
sentibank/dict_arXiv/Henry/Henry_v2006.json
sentibank/dict_arXiv/Henry/Henry_v2006.pickle
sentibank/dict_arXiv/MASTER/MASTER_v2022.csv
sentibank/dict_arXiv/MASTER/MASTER_v2022.json
sentibank/dict_arXiv/MASTER/MASTER_v2022.pickle
sentibank/dict_arXiv/NoVAD/NoVAD_v2013.csv
sentibank/dict_arXiv/NoVAD/NoVAD_v2013_bidimensional.json
sentibank/dict_arXiv/NoVAD/NoVAD_v2013_bidimensional.pickle
sentibank/dict_arXiv/NoVAD/NoVAD_v2013_boosted.json
sentibank-1.1.0.dist-info/licenses/LICENSE
sentibank-1.1.0.dist-info/METADATA
sentibank-1.1.0.dist-info/WHEEL
sentibank-1.1.0.dist-info/entry_points.txt
sentibank-1.1.0.dist-info/top_level.txt
sentibank-1.1.0.dist-info/RECORD
