Metadata-Version: 2.4
Name: sentibank
Version: 1.1.0
Summary: Unifying sentiment lexicons and dictionaries into an accessible open python package
Home-page: https://github.com/socius-org/sentibank
Download-URL: https://github.com/socius-org/sentibank/archive/refs/tags/0.2.4.tar.gz
Author: Nick Oh
Author-email: Nick Oh <nick.sh.oh@socius.org>
Maintainer-email: Nick Oh <nick.sh.oh@socius.org>
License: CC BY-NC-SA 4.0
Project-URL: Homepage, https://github.com/socius-org/sentibank
Project-URL: Documentation, https://doc.socius.org/sentibank/about.html
Project-URL: Repository, https://github.com/socius-org/sentibank
Project-URL: Issues, https://github.com/socius-org/sentibank/issues
Project-URL: Changelog, https://github.com/socius-org/sentibank/releases
Keywords: sentiment analysis,sentiment dictionary,sentiment lexicon,semantic orientation,nlp,text analysis
Classifier: Development Status :: 4 - Beta
Classifier: Intended Audience :: Developers
Classifier: Intended Audience :: Science/Research
Classifier: Topic :: Scientific/Engineering :: Information Analysis
Classifier: Topic :: Text Processing :: Linguistic
Classifier: License :: Other/Proprietary License
Classifier: Programming Language :: Python :: 3
Classifier: Programming Language :: Python :: 3.8
Classifier: Programming Language :: Python :: 3.9
Classifier: Programming Language :: Python :: 3.10
Classifier: Programming Language :: Python :: 3.11
Classifier: Programming Language :: Python :: 3.12
Classifier: Operating System :: OS Independent
Requires-Python: >=3.8
License-File: LICENSE
Requires-Dist: spacy>=3.7.2
Requires-Dist: spacymoji>=3.1.0
Requires-Dist: rich>=13.4.2
Requires-Dist: pandas>=2.1.4
Requires-Dist: pyenchant>=3.2.2
Provides-Extra: dev
Requires-Dist: pytest>=7.4.0; extra == "dev"
Requires-Dist: pytest-cov>=4.1.0; extra == "dev"
Requires-Dist: pytest-mock>=3.11.1; extra == "dev"
Requires-Dist: coverage>=7.3.0; extra == "dev"
Requires-Dist: black>=23.7.0; extra == "dev"
Requires-Dist: isort>=5.12.0; extra == "dev"
Requires-Dist: flake8>=6.1.0; extra == "dev"
Requires-Dist: mypy>=1.5.0; extra == "dev"
Requires-Dist: sphinx>=7.1.0; extra == "dev"
Requires-Dist: sphinx-rtd-theme>=1.3.0; extra == "dev"
Provides-Extra: docs
Requires-Dist: sphinx>=7.1.0; extra == "docs"
Requires-Dist: sphinx-rtd-theme>=1.3.0; extra == "docs"
Requires-Dist: myst-parser>=2.0.0; extra == "docs"
Requires-Dist: sphinx-autodoc-typehints>=1.24.0; extra == "docs"
Dynamic: author
Dynamic: download-url
Dynamic: home-page
Dynamic: license-file
Dynamic: requires-python
